princess.py
princess-0.6.dist-info/LICENSE
princess-0.6.dist-info/WHEEL
princess-0.6.dist-info/METADATA
princess-0.6.dist-info/RECORD
