Metadata-Version: 2.1
Name: princess
Version: 0.6
Summary: Please Run IPython Notebook in the Current Environment with Stdout & Stderr
Author-email: European XFEL GmbH <da-support@xfel.eu>
Requires-Python: >=3.7
Classifier: Framework :: Jupyter
Classifier: License :: OSI Approved :: BSD License
Requires-Dist: nbclient
Requires-Dist: nbformat
Requires-Dist: jupyter_client >=6.1.0
Requires-Dist: ipykernel
Project-URL: Source, https://github.com/European-XFEL/princess
